[
  {
    "id": "4-seat-car",
    "name": "4 Seater Car",
    "type": "minibus",
    "capacity": "4 Seats",
    "image": "/data/vehicles/vehicles_image/swift-car.webp",
    "description": "Comfortable sedan for small groups and family trips, ideal for short transfers and city travel.",
    "priority": 1,
    "amenities": [
      "Air Conditioning",
      "Professional Driver"
    ]
  },
  {
    "id": "7-seat-innova",
    "name": "7 Seater Innova",
    "type": "minibus",
    "capacity": "7 Seats",
    "image": "/data/vehicles/vehicles_image/innova-7seater.webp",
    "description": "Spacious and reliable Innova, perfect for family outings and small group travel.",
    "priority": 2,
    "amenities": [
      "Air Conditioning",
      "Professional Driver"
    ]
  },
  {
    "id": "14-seat-traveller",
    "name": "14 Seater Traveller",
    "type": "minibus",
    "capacity": "14 Seats",
    "image": "/data/vehicles/vehicles_image/traveller-14seater.webp",
    "description": "Comfortable traveller for small group trips, perfect for family functions and short tours.",
    "priority": 3,
    "amenities": [
      "Air Conditioning",
      "Professional Driver"
    ]
  },
  {
    "id": "16-seat-urbania",
    "name": "16 Seater Urbania",
    "type": "minibus",
    "capacity": "16 Seats",
    "image": "/data/vehicles/vehicles_image/urbania-16seater.webp",
    "description": "Modern and spacious Urbania offering a smooth, comfortable ride for group outings.",
    "priority": 4,
    "amenities": [
      "Air Conditioning",
      "Professional Driver"
    ]
  },
  {
    "id": "24-seat-traveller",
    "name": "24 Seater Traveller",
    "type": "minibus",
    "capacity": "24 Seats",
    "image": "/data/vehicles/vehicles_image/traveller-24seater.webp",
    "description": "Wider body traveller with comfortable seating, well suited for sightseeing and group tours.",
    "priority": 5,
    "amenities": [
      "Air Conditioning",
      "Professional Driver"
    ]
  },
  {
    "id": "34-seat-bus",
    "name": "34 Seater Bus",
    "type": "coach",
    "capacity": "34 Seats",
    "image": "/data/vehicles/vehicles_image/34seater-bus.webp",
    "description": "Mid-size bus suited for group travel, outings, and intercity trips.",
    "priority": 6,
    "amenities": [
      "Air Conditioning",
      "Professional Driver"
    ]
  },
  {
    "id": "45-seat-glider",
    "name": "45 Seater Glider",
    "type": "coach",
    "capacity": "45 Seats",
    "image": "/data/vehicles/vehicles_image/45seater-but.webp",
    "description": "Smooth and spacious glider coach, a great choice for larger group journeys.",
    "priority": 7,
    "amenities": [
      "Air Conditioning",
      "Professional Driver"
    ]
  },
  {
    "id": "49-seat-bus",
    "name": "49 Seater Bus",
    "type": "coach",
    "capacity": "49 Seats",
    "image": "/data/vehicles/vehicles_image/49seater-bus.webp",
    "description": "Large capacity bus ideal for big groups, tours, and long-distance travel.",
    "priority": 8,
    "amenities": [
      "Air Conditioning",
      "Professional Driver"
    ]
  }
]
